pythermo/__init__.py
pythermo/constants.py
pythermo/crystal.py
pythermo/tT_model.py
pythermo/tT_path.py
pythermo-0.2.1.dist-info/LICENSE
pythermo-0.2.1.dist-info/METADATA
pythermo-0.2.1.dist-info/WHEEL
pythermo-0.2.1.dist-info/top_level.txt
pythermo-0.2.1.dist-info/RECORD
