Metadata-Version: 2.2
Name: pythermo
Version: 0.2.1
Summary: Tools for performing computational tasks in the field of low-temperature thermochronology.
Author-email: William Guenthner <wrg@illinois.edu>
Project-URL: Homepage, https://github.com/OpenThermochronology/PyThermo
Project-URL: Issues, https://github.com/OpenThermochronology/PyThermo/issues
Keywords: thermochronology,zircon,apatite,geology,diffusion,geochronology
Classifier: Programming Language :: Python :: 3
Classifier: License :: OSI Approved :: GNU General Public License v3 (GPLv3)
Classifier: Operating System :: OS Independent
Requires-Python: >=3.7
License-File: LICENSE
Requires-Dist: numpy
Requires-Dist: scipy
Requires-Dist: matplotlib
